CMakeLists.txt
MANIFEST.in
README.md
bindings.py.cmake
setup.py
setup.py.cmake
/Users/sp/Code/exifyay/bindings.py
/Users/sp/Code/exifyay/bindings/__init__.py
/Users/sp/Code/exifyay/bindings/exifyay.so
/Users/sp/Code/exifyay/bindings/test.py
JpegEncoderEXIF/CMakeLists.txt
JpegEncoderEXIF/JpegEncoderEXIF.c
JpegEncoderEXIF/JpegEncoderEXIF.h
bindings/CMakeLists.txt
bindings/__init__.py
bindings/cexif.pxd
bindings/exifyay.c
bindings/exifyay.pyx
bindings/test.py
cmake/FindCython.cmake
cmake/UseCython.cmake
exifyay.egg-info/PKG-INFO
exifyay.egg-info/SOURCES.txt
exifyay.egg-info/dependency_links.txt
exifyay.egg-info/not-zip-safe
exifyay.egg-info/top_level.txt
libexif/CMakeLists.txt
libexif/_stdint.h
libexif/config.h.cmake
libexif/exif-byte-order.c
libexif/exif-byte-order.h
libexif/exif-content.c
libexif/exif-content.h
libexif/exif-data-type.h
libexif/exif-data.c
libexif/exif-data.h
libexif/exif-entry.c
libexif/exif-entry.h
libexif/exif-format.c
libexif/exif-format.h
libexif/exif-ifd.c
libexif/exif-ifd.h
libexif/exif-loader.c
libexif/exif-loader.h
libexif/exif-log.c
libexif/exif-log.h
libexif/exif-mem.c
libexif/exif-mem.h
libexif/exif-mnote-data-priv.h
libexif/exif-mnote-data.c
libexif/exif-mnote-data.h
libexif/exif-system.h
libexif/exif-tag.c
libexif/exif-tag.h
libexif/exif-utils.c
libexif/exif-utils.h
libexif/exif.h
libexif/i18n.h
libexif/canon/exif-mnote-data-canon.c
libexif/canon/exif-mnote-data-canon.h
libexif/canon/mnote-canon-entry.c
libexif/canon/mnote-canon-entry.h
libexif/canon/mnote-canon-tag.c
libexif/canon/mnote-canon-tag.h
libexif/fuji/exif-mnote-data-fuji.c
libexif/fuji/exif-mnote-data-fuji.h
libexif/fuji/mnote-fuji-entry.c
libexif/fuji/mnote-fuji-entry.h
libexif/fuji/mnote-fuji-tag.c
libexif/fuji/mnote-fuji-tag.h
libexif/olympus/exif-mnote-data-olympus.c
libexif/olympus/exif-mnote-data-olympus.h
libexif/olympus/mnote-olympus-entry.c
libexif/olympus/mnote-olympus-entry.h
libexif/olympus/mnote-olympus-tag.c
libexif/olympus/mnote-olympus-tag.h
libexif/pentax/exif-mnote-data-pentax.c
libexif/pentax/exif-mnote-data-pentax.h
libexif/pentax/mnote-pentax-entry.c
libexif/pentax/mnote-pentax-entry.h
