Metadata-Version: 1.0
Name: exifyay
Version: 0.2.0
Summary: Yay, Exif!
Home-page: http://github.com/Memoto/exifyay
Author: Simon Pantzare
Author-email: simon@narrativeteam.com
License: LGPL
Keywords: exif
Platform: UNKNOWN
